PyTeCK-0.2.4.dist-info/LICENSE.txt
PyTeCK-0.2.4.dist-info/METADATA
PyTeCK-0.2.4.dist-info/RECORD
PyTeCK-0.2.4.dist-info/WHEEL
PyTeCK-0.2.4.dist-info/entry_points.txt
PyTeCK-0.2.4.dist-info/top_level.txt
pyteck/__init__.py
pyteck/__main__.py
pyteck/_version.py
pyteck/detect_peaks.py
pyteck/eval_model.py
pyteck/exceptions.py
pyteck/parse_files_XML.py
pyteck/simulation.py
pyteck/utils.py
pyteck/validation.py
pyteck/tests/__init__.py
pyteck/tests/dataset_file.txt
pyteck/tests/spec_keys.yaml
pyteck/tests/test_detect_peaks.py
pyteck/tests/test_eval_model.py
pyteck/tests/test_parse_files_xml.py
pyteck/tests/test_simulation.py
pyteck/tests/test_validation.py
pyteck/tests/testfile_rcm.xml
pyteck/tests/testfile_rcm.yaml
pyteck/tests/testfile_st.xml
pyteck/tests/testfile_st.yaml
pyteck/tests/testfile_st2.xml
pyteck/tests/testfile_st2.yaml
