Metadata-Version: 2.1
Name: PyTeCK
Version: 0.2.4
Summary: Evaluation of chemical kinetic models with experimental data
Home-page: https://github.com/kyleniemeyer/PyTeCK
Author: Kyle E. Niemeyer
Author-email: kyle.niemeyer@gmail.com
License: MIT License
Keywords: chemical_kinetics
Platform: UNKNOWN
Classifier: Development Status :: 4 - Beta
Classifier: Intended Audience :: Developers
Classifier: Intended Audience :: Science/Research
Classifier: License :: OSI Approved :: MIT License
Classifier: Natural Language :: English
Classifier: Programming Language :: Python :: 3
Classifier: Programming Language :: Python :: 3.5
Classifier: Programming Language :: Python :: 3.6
Classifier: Topic :: Scientific/Engineering :: Chemistry
Requires-Dist: pyyaml (<4.0,>=3.12)
Requires-Dist: pint (>=0.7.2)
Requires-Dist: numpy (>=1.13.0)
Requires-Dist: tables
Requires-Dist: pyked (>=0.4.1)
Requires-Dist: scipy (>=0.19.0)
